shades/__init__.py
shades/canvas.py
shades/noise_fields.py
shades/shades.py
shades/utils.py
shades-1.2.dist-info/LICENSE
shades-1.2.dist-info/METADATA
shades-1.2.dist-info/WHEEL
shades-1.2.dist-info/top_level.txt
shades-1.2.dist-info/RECORD
