Metadata-Version: 2.1
Name: shades
Version: 1.2
Summary: A Python module for generative 2d image creation
Home-page: https://github.com/benrrutter/shades
Author: Ben Rutter
License: UNKNOWN
Platform: UNKNOWN
Requires-Python: >=3.6
License-File: LICENSE
Requires-Dist: numpy (>=1.20.0)
Requires-Dist: Pillow (>=8.0.0)
